bestllm/__init__.py
bestllm/hardware.py
bestllm/models.py
bestllm/selector.py
bestllm-0.0.1.dist-info/WHEEL
bestllm-0.0.1.dist-info/entry_points.txt
bestllm-0.0.1.dist-info/METADATA
bestllm-0.0.1.dist-info/RECORD
