Metadata-Version: 2.3
Name: bestllm
Version: 0.0.1
Summary: Tries to pick the best local llm for your computer and environment.
Author: Timothy Crosley
Author-email: Timothy Crosley <timothy.crosley@gmail.com>
Requires-Python: >=3.11
